include/mmcfilters/attributes/AreaComputer.hpp
include/mmcfilters/attributes/AttributeComputedIncrementally.hpp
include/mmcfilters/attributes/AttributeComputer.hpp
include/mmcfilters/attributes/AttributeFactory.hpp
include/mmcfilters/attributes/AttributeNames.hpp
include/mmcfilters/attributes/BitquadsComputer.hpp
include/mmcfilters/attributes/BoundingBoxComputer.hpp
include/mmcfilters/attributes/ComputerAttributeBasedBitQuads.hpp
include/mmcfilters/attributes/ComputerMSER.hpp
include/mmcfilters/attributes/GrayLevelStatsComputer.hpp
include/mmcfilters/attributes/MomentBasedAttributeComputer.hpp
include/mmcfilters/attributes/TreeTopologyComputer.hpp
include/mmcfilters/attributes/VolumeComputer.hpp
include/mmcfilters/contours/ContoursComputedIncrementally.hpp
include/mmcfilters/filters/AttributeFilters.hpp
include/mmcfilters/filters/AttributeOpeningPrimitivesFamily.hpp
include/mmcfilters/filters/ExtinctionValues.hpp
include/mmcfilters/filters/UltimateAttributeOpening.hpp
include/mmcfilters/trees/BuilderMorphologicalTreeByUnionFind.hpp
include/mmcfilters/trees/MorphologicalTree.hpp
include/mmcfilters/trees/MorphologicalTree.tpp
include/mmcfilters/trees/NodeMT.hpp
include/mmcfilters/trees/NodeMTArena.hpp
include/mmcfilters/trees/NodeRes.hpp
include/mmcfilters/trees/ResidualTree.hpp
include/mmcfilters/utils/AdjacencyRelation.hpp
include/mmcfilters/utils/Common.hpp
include/mmcfilters/utils/ComputerDerivatives.hpp
include/mmcfilters/utils/Image.hpp
include/mmcfilters/utils/PixelSetManager.hpp
lib/cmake/mmcfilters/mmcfiltersTargets-release.cmake
lib/cmake/mmcfilters/mmcfiltersTargets.cmake
lib/libmmcfilters_lib.a
mmcfilters.cpython-312-darwin.so
python/mmcfilters/__init__.py
python/mmcfilters/_version.py
python/mmcfilters/test.py
mmcfilters-0.1.24.dist-info/METADATA
mmcfilters-0.1.24.dist-info/WHEEL
mmcfilters-0.1.24.dist-info/licenses/LICENSE
mmcfilters-0.1.24.dist-info/RECORD
