Metadata-Version: 2.2
Name: mmcfilters
Version: 0.1.24
Summary: Library for connected image filtering based on morphological trees
Keywords: morphological trees,mathematical morphology,image processing,computer vision
Author-Email: Wonder Alexandre Luz Alves <worderalexandre@gmail.com>
License:                     GNU GENERAL PUBLIC LICENSE
Classifier: Development Status :: 3 - Alpha
Classifier: Intended Audience :: Science/Research
Classifier: Topic :: Scientific/Engineering :: Image Processing
Classifier: Programming Language :: Python
Classifier: Programming Language :: C++
Requires-Python: >=3.9
